README.rst
setup.py
pour/__init__.py
pour/app.py
pour/pour.py
pour/test.py
pour.egg-info/PKG-INFO
pour.egg-info/SOURCES.txt
pour.egg-info/dependency_links.txt
pour.egg-info/entry_points.txt
pour.egg-info/pbr.json
pour.egg-info/requires.txt
pour.egg-info/top_level.txt