Metadata-Version: 1.0
Name: pour
Version: 0.2.1
Summary: A lightweight Flask app generator.
Home-page: http://www.github.com/keyanp/pour
Author: Keyan Pishdadian
Author-email: kpishdadian@gmail.com
License: MIT
Platform: UNKNOWN
